{
  "POIs": [
    {
      "fit": [
        0.0,
        0.17459341883659363,
        1.353898286819458
      ],
      "name": "r"
    }
  ],
  "params": [
    {
      "fit": [
        -0.9576704502105713,
        0.024986861273646355,
        1.0013854503631592
      ],
      "groups": [
        "allb1",
        "other",
        "syst"
      ],
      "impact_r": 0.007550850510597229,
      "name": "norm_zjets",
      "prefit": [
        -0.9999999999999999,
        0.0,
        0.9999999999999999
      ],
      "r": [
        0.18140670657157898,
        0.17459341883659363,
        0.1670425683259964
      ],
      "type": "Gaussian"
    },
    {
      "fit": [
        -0.454851895570755,
        0.47179779410362244,
        1.3765068054199219
      ],
      "groups": [
        "allb1",
        "ca15btag",
        "syst"
      ],
      "impact_r": 0.07212714850902557,
      "name": "sjbtag",
      "prefit": [
        -1.0,
        0.0,
        1.0
      ],
      "r": [
        0.24675095081329346,
        0.17462380230426788,
        0.10883254557847977
      ],
      "type": "Gaussian"
    },
    {
      "fit": [
        0.3848161995410919,
        1.0963118076324463,
        1.802178144454956
      ],
      "groups": [
        "allb1",
        "ca15btag",
        "syst"
      ],
      "impact_r": 0.13475476205348969,
      "name": "sjmistag",
      "prefit": [
        -1.0,
        0.0,
        1.0
      ],
      "r": [
        0.3093455731868744,
        0.1745908111333847,
        0.047181423753499985
      ],
      "type": "Gaussian"
    },
    {
      "fit": [
        -1.2748464345932007,
        -0.37528082728385925,
        0.49729055166244507
      ],
      "groups": [
        "ak4btag",
        "allb1",
        "syst"
      ],
      "impact_r": 0.010665729641914368,
      "name": "btag",
      "prefit": [
        -1.0,
        0.0,
        1.0
      ],
      "r": [
        0.16669818758964539,
        0.1746234893798828,
        0.18528921902179718
      ],
      "type": "Gaussian"
    },
    {
      "fit": [
        -1.1443406343460083,
        -0.20691530406475067,
        0.7283037304878235
      ],
      "groups": [
        "ak4btag",
        "allb1",
        "syst"
      ],
      "impact_r": 0.01981675624847412,
      "name": "mistag",
      "prefit": [
        -1.0,
        0.0,
        1.0
      ],
      "r": [
        0.15488219261169434,
        0.17469894886016846,
        0.19431985914707184
      ],
      "type": "Gaussian"
    },
    {
      "fit": [
        -1.141860008239746,
        -0.2027130424976349,
        0.7096966505050659
      ],
      "groups": [
        "allb1",
        "other",
        "syst"
      ],
      "impact_r": 0.023860350251197815,
      "name": "norm_wjets",
      "prefit": [
        -0.9999999999999999,
        0.0,
        0.9999999999999999
      ],
      "r": [
        0.15753114223480225,
        0.17459429800510406,
        0.19845464825630188
      ],
      "type": "Gaussian"
    },
    {
      "fit": [
        -1.0551753044128418,
        -0.0725666806101799,
        0.9056981801986694
      ],
      "groups": [
        "allb1",
        "other",
        "syst"
      ],
      "impact_r": 0.0016900449991226196,
      "name": "SFTopMisTag",
      "prefit": [
        -0.9999999999999999,
        0.0,
        0.9999999999999999
      ],
      "r": [
        0.17628338932991028,
        0.17459334433078766,
        0.17401434481143951
      ],
      "type": "Gaussian"
    },
    {
      "fit": [
        -1.289651870727539,
        -0.3512977957725525,
        0.5878893733024597
      ],
      "groups": [
        "allb1",
        "other",
        "syst"
      ],
      "impact_r": 0.009886011481285095,
      "name": "SFTopTag",
      "prefit": [
        -0.9999999999999999,
        0.0,
        0.9999999999999999
      ],
      "r": [
        0.18448233604431152,
        0.17459632456302643,
        0.1659741848707199
      ],
      "type": "Gaussian"
    },
    {
      "fit": [
        -1.3773940801620483,
        -0.4479433298110962,
        0.4717997610569
      ],
      "groups": [
        "allb1",
        "other",
        "syst"
      ],
      "impact_r": 0.011532112956047058,
      "name": "ca15_jec",
      "prefit": [
        -0.9999999999999999,
        0.0,
        0.9999999999999999
      ],
      "r": [
        0.18612445890903473,
        0.17459234595298767,
        0.16442523896694183
      ],
      "type": "Gaussian"
    },
    {
      "fit": [
        -0.9618455767631531,
        -0.0295014176517725,
        0.8433959484100342
      ],
      "groups": [
        "allb1",
        "syst"
      ],
      "impact_r": 0.004345491528511047,
      "name": "gjethf",
      "prefit": [
        -0.9999999999999999,
        0.0,
        0.9999999999999999
      ],
      "r": [
        0.1725614368915558,
        0.17459382116794586,
        0.1789393126964569
      ],
      "type": "Gaussian"
    },
    {
      "fit": [
        -1.2462214231491089,
        -0.28241220116615295,
        0.6780850291252136
      ],
      "groups": [
        "dummy"
      ],
      "impact_r": 0.007352575659751892,
      "name": "lumi",
      "prefit": [
        -0.9999999999999999,
        0.0,
        0.9999999999999999
      ],
      "r": [
        0.18194590508937836,
        0.17459332942962646,
        0.16849403083324432
      ],
      "type": "Gaussian"
    },
    {
      "fit": [
        -0.8239773511886597,
        -0.14342191815376282,
        0.41347986459732056
      ],
      "groups": [
        "allb1",
        "syst"
      ],
      "impact_r": 0.0027345269918441772,
      "name": "met",
      "prefit": [
        -0.9999999999999999,
        0.0,
        0.9999999999999999
      ],
      "r": [
        0.17732751369476318,
        0.174592986702919,
        0.17405278980731964
      ],
      "type": "Gaussian"
    },
    {
      "fit": [
        -0.9840035438537598,
        0.013510380871593952,
        1.0083132982254028
      ],
      "groups": [
        "allb1",
        "other",
        "syst"
      ],
      "impact_r": 0.0007932782173156738,
      "name": "norm_QCDe",
      "prefit": [
        -0.9999999999999999,
        0.0,
        0.9999999999999999
      ],
      "r": [
        0.1753866970539093,
        0.17459341883659363,
        0.1747848242521286
      ],
      "type": "Gaussian"
    },
    {
      "fit": [
        -0.8759498596191406,
        0.1154501885175705,
        1.0274097919464111
      ],
      "groups": [
        "allb1",
        "other",
        "syst"
      ],
      "impact_r": 0.04957839846611023,
      "name": "norm_QCDgamma",
      "prefit": [
        -0.9999999999999999,
        0.0,
        0.9999999999999999
      ],
      "r": [
        0.1990782469511032,
        0.174595907330513,
        0.12501750886440277
      ],
      "type": "Gaussian"
    },
    {
      "fit": [
        -1.5459585189819336,
        -0.7945891618728638,
        -0.1485101580619812
      ],
      "groups": [
        "allb1",
        "other",
        "syst"
      ],
      "impact_r": 0.0006530284881591797,
      "name": "norm_QCDmu",
      "prefit": [
        -0.9999999999999999,
        0.0,
        0.9999999999999999
      ],
      "r": [
        0.17448413372039795,
        0.17460571229457855,
        0.17525874078273773
      ],
      "type": "Gaussian"
    },
    {
      "fit": [
        -0.9762787222862244,
        0.01592249423265457,
        0.9934728741645813
      ],
      "groups": [
        "allb1",
        "other",
        "syst"
      ],
      "impact_r": 0.005235299468040466,
      "name": "norm_QCDsig",
      "prefit": [
        -0.9999999999999999,
        0.0,
        0.9999999999999999
      ],
      "r": [
        0.17282016575336456,
        0.17459343373775482,
        0.1798287332057953
      ],
      "type": "Gaussian"
    },
    {
      "fit": [
        -1.097772479057312,
        -0.17980003356933594,
        0.6599864363670349
      ],
      "groups": [
        "allb1",
        "other",
        "syst"
      ],
      "impact_r": 0.02311578392982483,
      "name": "norm_stop",
      "prefit": [
        -0.9999999999999999,
        0.0,
        0.9999999999999999
      ],
      "r": [
        0.19612033665180206,
        0.17459145188331604,
        0.1514756679534912
      ],
      "type": "Gaussian"
    },
    {
      "fit": [
        -1.0386435985565186,
        -0.06799096614122391,
        0.8943941593170166
      ],
      "groups": [
        "allb1",
        "other",
        "syst"
      ],
      "impact_r": 0.028480619192123413,
      "name": "norm_tt",
      "prefit": [
        -0.9999999999999999,
        0.0,
        0.9999999999999999
      ],
      "r": [
        0.15086212754249573,
        0.17459332942962646,
        0.20307394862174988
      ],
      "type": "Gaussian"
    },
    {
      "fit": [
        -1.0557582378387451,
        -0.10086899995803833,
        0.8260601758956909
      ],
      "groups": [
        "allb1",
        "other",
        "syst"
      ],
      "impact_r": 0.015616148710250854,
      "name": "norm_vv",
      "prefit": [
        -0.9999999999999999,
        0.0,
        0.9999999999999999
      ],
      "r": [
        0.1630784124135971,
        0.17459522187709808,
        0.19021137058734894
      ],
      "type": "Gaussian"
    },
    {
      "fit": [
        -1.9514604806900024,
        -1.0659525394439697,
        -0.17655719816684723
      ],
      "groups": [
        "allb1",
        "lep",
        "syst"
      ],
      "impact_r": 0.04320196807384491,
      "name": "sf_ele",
      "prefit": [
        -0.9999999999999999,
        0.0,
        0.9999999999999999
      ],
      "r": [
        0.13308683037757874,
        0.17465044558048248,
        0.2178524136543274
      ],
      "type": "Gaussian"
    },
    {
      "fit": [
        -0.5932489633560181,
        0.27328020334243774,
        1.128158450126648
      ],
      "groups": [
        "allb1",
        "lep",
        "syst"
      ],
      "impact_r": 0.061838433146476746,
      "name": "sf_mu",
      "prefit": [
        -0.9999999999999999,
        0.0,
        0.9999999999999999
      ],
      "r": [
        0.11376442760229111,
        0.1745946854352951,
        0.23643311858177185
      ],
      "type": "Gaussian"
    },
    {
      "fit": [
        -1.4925323724746704,
        -0.533711314201355,
        0.4268375039100647
      ],
      "groups": [
        "allb1",
        "lep",
        "syst"
      ],
      "impact_r": 0.02091333270072937,
      "name": "track_ele",
      "prefit": [
        -0.9999999999999999,
        0.0,
        0.9999999999999999
      ],
      "r": [
        0.1550552248954773,
        0.17459389567375183,
        0.1955072283744812
      ],
      "type": "Gaussian"
    },
    {
      "fit": [
        -0.8183658719062805,
        0.13760505616664886,
        1.0916175842285156
      ],
      "groups": [
        "allb1",
        "lep",
        "syst"
      ],
      "impact_r": 0.029891014099121094,
      "name": "track_mu",
      "prefit": [
        -0.9999999999999999,
        0.0,
        0.9999999999999999
      ],
      "r": [
        0.14599572122097015,
        0.17459352314472198,
        0.20448453724384308
      ],
      "type": "Gaussian"
    },
    {
      "fit": [
        -1.5976314544677734,
        -0.6767436265945435,
        0.24174678325653076
      ],
      "groups": [
        "allb1",
        "lep",
        "syst"
      ],
      "impact_r": 0.022370710968971252,
      "name": "trig_ele",
      "prefit": [
        -0.9999999999999999,
        0.0,
        0.9999999999999999
      ],
      "r": [
        0.1526658684015274,
        0.1745961755514145,
        0.19696688652038574
      ],
      "type": "Gaussian"
    },
    {
      "fit": [
        -0.980103075504303,
        -0.007826810702681541,
        0.9622803330421448
      ],
      "groups": [
        "allb1",
        "other",
        "syst"
      ],
      "impact_r": 0.0014223754405975342,
      "name": "trig_pho",
      "prefit": [
        -0.9999999999999999,
        0.0,
        0.9999999999999999
      ],
      "r": [
        0.1744208037853241,
        0.17459285259246826,
        0.1760152280330658
      ],
      "type": "Gaussian"
    },
    {
      "fit": [
        -0.08366745710372925,
        -0.08366745710372925,
        0.7266770601272583
      ],
      "groups": [
        "allb1",
        "lep",
        "syst"
      ],
      "impact_r": 0.001853346824645996,
      "name": "veto_tau",
      "prefit": [
        -0.9999999999999999,
        0.0,
        0.9999999999999999
      ],
      "r": [
        0.17516137659549713,
        0.17459237575531006,
        0.17644572257995605
      ],
      "type": "Gaussian"
    },
    {
      "fit": [
        -0.41407155990600586,
        0.4201134145259857,
        1.1440045833587646
      ],
      "groups": [
        "allb1",
        "syst",
        "vjethf"
      ],
      "impact_r": 0.0025243014097213745,
      "name": "wjethf",
      "prefit": [
        -0.9999999999999999,
        0.0,
        0.9999999999999999
      ],
      "r": [
        0.17711952328681946,
        0.17459522187709808,
        0.17347916960716248
      ],
      "type": "Gaussian"
    },
    {
      "fit": [
        -0.8451513648033142,
        -0.05957338958978653,
        0.6669818758964539
      ],
      "groups": [
        "allb1",
        "syst",
        "vjethf"
      ],
      "impact_r": 0.003735363483428955,
      "name": "zjethf",
      "prefit": [
        -0.9999999999999999,
        0.0,
        0.9999999999999999
      ],
      "r": [
        0.17236950993537903,
        0.17458724975585938,
        0.17832261323928833
      ],
      "type": "Gaussian"
    },
    {
      "fit": [
        -0.7132823467254639,
        -0.05173138901591301,
        0.6484081745147705
      ],
      "groups": [
        "allb1",
        "mcstat"
      ],
      "impact_r": 0.035164058208465576,
      "name": "monotop_stat_error_photonModelCR_bin1",
      "prefit": [
        -1.0,
        0.0,
        1.0
      ],
      "r": [
        0.14364200830459595,
        0.17459341883659363,
        0.2097574770450592
      ],
      "type": "Gaussian"
    },
    {
      "fit": [
        -0.7023533582687378,
        -0.03456629067659378,
        0.6530978679656982
      ],
      "groups": [
        "allb1",
        "mcstat"
      ],
      "impact_r": 0.03594578802585602,
      "name": "monotop_stat_error_photonModelCR_bin2",
      "prefit": [
        -1.0,
        0.0,
        1.0
      ],
      "r": [
        0.14177092909812927,
        0.17459341883659363,
        0.21053920686244965
      ],
      "type": "Gaussian"
    },
    {
      "fit": [
        -0.029655994847416878,
        0.6469910144805908,
        1.3711886405944824
      ],
      "groups": [
        "allb1",
        "mcstat"
      ],
      "impact_r": 0.025969594717025757,
      "name": "monotop_stat_error_photonModelCR_bin3",
      "prefit": [
        -1.0,
        0.0,
        1.0
      ],
      "r": [
        0.15212687849998474,
        0.17459341883659363,
        0.20056301355361938
      ],
      "type": "Gaussian"
    },
    {
      "fit": [
        -0.44076892733573914,
        0.21958287060260773,
        0.9220973253250122
      ],
      "groups": [
        "allb1",
        "mcstat"
      ],
      "impact_r": 0.011938601732254028,
      "name": "monotop_stat_error_photonModelCR_bin4",
      "prefit": [
        -1.0,
        0.0,
        1.0
      ],
      "r": [
        0.1661936640739441,
        0.17459341883659363,
        0.18653202056884766
      ],
      "type": "Gaussian"
    },
    {
      "fit": [
        -0.41445016860961914,
        0.2811587452888489,
        1.025520920753479
      ],
      "groups": [
        "allb1",
        "mcstat"
      ],
      "impact_r": 0.01889936625957489,
      "name": "monotop_stat_error_photonModelCR_bin5",
      "prefit": [
        -1.0,
        0.0,
        1.0
      ],
      "r": [
        0.19349278509616852,
        0.17459341883659363,
        0.15817268192768097
      ],
      "type": "Gaussian"
    },
    {
      "fit": [
        -1.028641700744629,
        -0.29048022627830505,
        0.5018529295921326
      ],
      "groups": [
        "allb1",
        "mcstat"
      ],
      "impact_r": 0.09328654408454895,
      "name": "monotop_stat_error_photonModelCR_bin6",
      "prefit": [
        -1.0,
        0.0,
        1.0
      ],
      "r": [
        0.2678799629211426,
        0.17459341883659363,
        0.0884011760354042
      ],
      "type": "Gaussian"
    },
    {
      "fit": [
        -0.8849377036094666,
        -0.06910576671361923,
        0.8080887794494629
      ],
      "groups": [
        "allb1",
        "mcstat"
      ],
      "impact_r": 0.22679853439331055,
      "name": "monotop_stat_error_photonModelCR_bin7",
      "prefit": [
        -1.0,
        0.0,
        1.0
      ],
      "r": [
        0.4013919532299042,
        0.17459341883659363,
        0.0001923621748574078
      ],
      "type": "Gaussian"
    },
    {
      "fit": [
        -0.7327210307121277,
        0.16416499018669128,
        1.0718504190444946
      ],
      "groups": [
        "allb1",
        "mcstat"
      ],
      "impact_r": 0.011142730712890625,
      "name": "monotop_stat_error_dimuonModelCR_bin1",
      "prefit": [
        -1.0,
        0.0,
        1.0
      ],
      "r": [
        0.18573614954948425,
        0.17459341883659363,
        0.16550904512405396
      ],
      "type": "Gaussian"
    },
    {
      "fit": [
        -0.715298593044281,
        0.1835957169532776,
        1.0935121774673462
      ],
      "groups": [
        "allb1",
        "mcstat"
      ],
      "impact_r": 0.010937631130218506,
      "name": "monotop_stat_error_dimuonModelCR_bin2",
      "prefit": [
        -1.0,
        0.0,
        1.0
      ],
      "r": [
        0.18553104996681213,
        0.17459341883659363,
        0.16584376990795135
      ],
      "type": "Gaussian"
    },
    {
      "fit": [
        -1.3573882579803467,
        -0.44910484552383423,
        0.4717915952205658
      ],
      "groups": [
        "allb1",
        "mcstat"
      ],
      "impact_r": 0.015608668327331543,
      "name": "monotop_stat_error_dimuonModelCR_bin3",
      "prefit": [
        -1.0,
        0.0,
        1.0
      ],
      "r": [
        0.19020208716392517,
        0.17459341883659363,
        0.16168949007987976
      ],
      "type": "Gaussian"
    },
    {
      "fit": [
        -1.4903678894042969,
        -0.5550761818885803,
        0.3911016583442688
      ],
      "groups": [
        "allb1",
        "mcstat"
      ],
      "impact_r": 0.013847604393959045,
      "name": "monotop_stat_error_dimuonModelCR_bin4",
      "prefit": [
        -1.0,
        0.0,
        1.0
      ],
      "r": [
        0.18844102323055267,
        0.17459341883659363,
        0.16348667442798615
      ],
      "type": "Gaussian"
    },
    {
      "fit": [
        -1.093420147895813,
        -0.12501391768455505,
        0.8474131226539612
      ],
      "groups": [
        "allb1",
        "mcstat"
      ],
      "impact_r": 0.010116204619407654,
      "name": "monotop_stat_error_dimuonModelCR_bin5",
      "prefit": [
        -1.0,
        0.0,
        1.0
      ],
      "r": [
        0.18470962345600128,
        0.17459341883659363,
        0.16684047877788544
      ],
      "type": "Gaussian"
    },
    {
      "fit": [
        -1.0794636011123657,
        -0.101483553647995,
        0.8792374730110168
      ],
      "groups": [
        "allb1",
        "mcstat"
      ],
      "impact_r": 0.01597006618976593,
      "name": "monotop_stat_error_dimuonModelCR_bin6",
      "prefit": [
        -1.0,
        0.0,
        1.0
      ],
      "r": [
        0.19056348502635956,
        0.17459341883659363,
        0.161076158285141
      ],
      "type": "Gaussian"
    },
    {
      "fit": [
        -1.0641098022460938,
        -0.0760049968957901,
        0.9132404923439026
      ],
      "groups": [
        "allb1",
        "mcstat"
      ],
      "impact_r": 0.018122941255569458,
      "name": "monotop_stat_error_dimuonModelCR_bin7",
      "prefit": [
        -1.0,
        0.0,
        1.0
      ],
      "r": [
        0.19271636009216309,
        0.17459341883659363,
        0.1594851016998291
      ],
      "type": "Gaussian"
    },
    {
      "fit": [
        -0.6282169818878174,
        0.27564573287963867,
        1.1901626586914062
      ],
      "groups": [
        "allb1",
        "mcstat"
      ],
      "impact_r": 0.009313270449638367,
      "name": "monotop_stat_error_dielectronModelCR_bin1",
      "prefit": [
        -1.0,
        0.0,
        1.0
      ],
      "r": [
        0.183906689286232,
        0.17459341883659363,
        0.16752316057682037
      ],
      "type": "Gaussian"
    },
    {
      "fit": [
        -0.44718170166015625,
        0.4515416920185089,
        1.3606603145599365
      ],
      "groups": [
        "allb1",
        "mcstat"
      ],
      "impact_r": 0.009977385401725769,
      "name": "monotop_stat_error_dielectronModelCR_bin2",
      "prefit": [
        -1.0,
        0.0,
        1.0
      ],
      "r": [
        0.1845708042383194,
        0.17459341883659363,
        0.16696849465370178
      ],
      "type": "Gaussian"
    },
    {
      "fit": [
        -0.9862094521522522,
        -0.06834540516138077,
        0.8613508343696594
      ],
      "groups": [
        "allb1",
        "mcstat"
      ],
      "impact_r": 0.011684909462928772,
      "name": "monotop_stat_error_dielectronModelCR_bin3",
      "prefit": [
        -1.0,
        0.0,
        1.0
      ],
      "r": [
        0.1862783282995224,
        0.17459341883659363,
        0.16558429598808289
      ],
      "type": "Gaussian"
    },
    {
      "fit": [
        -0.5079509615898132,
        0.41273829340934753,
        1.3414920568466187
      ],
      "groups": [
        "allb1",
        "mcstat"
      ],
      "impact_r": 0.0121888667345047,
      "name": "monotop_stat_error_dielectronModelCR_bin4",
      "prefit": [
        -1.0,
        0.0,
        1.0
      ],
      "r": [
        0.18678228557109833,
        0.17459341883659363,
        0.16519105434417725
      ],
      "type": "Gaussian"
    },
    {
      "fit": [
        -0.9796651005744934,
        -0.01733281835913658,
        0.9506082534790039
      ],
      "groups": [
        "allb1",
        "mcstat"
      ],
      "impact_r": 0.010237529873847961,
      "name": "monotop_stat_error_dielectronModelCR_bin5",
      "prefit": [
        -1.0,
        0.0,
        1.0
      ],
      "r": [
        0.1848309487104416,
        0.17459341883659363,
        0.16667909920215607
      ],
      "type": "Gaussian"
    },
    {
      "fit": [
        -0.8559170961380005,
        0.12236659973859787,
        1.1017005443572998
      ],
      "groups": [
        "allb1",
        "mcstat"
      ],
      "impact_r": 0.011947035789489746,
      "name": "monotop_stat_error_dielectronModelCR_bin6",
      "prefit": [
        -1.0,
        0.0,
        1.0
      ],
      "r": [
        0.18654045462608337,
        0.17459341883659363,
        0.16489163041114807
      ],
      "type": "Gaussian"
    },
    {
      "fit": [
        -0.8634368181228638,
        0.11956814676523209,
        1.1038005352020264
      ],
      "groups": [
        "allb1",
        "mcstat"
      ],
      "impact_r": 0.014925166964530945,
      "name": "monotop_stat_error_dielectronModelCR_bin7",
      "prefit": [
        -1.0,
        0.0,
        1.0
      ],
      "r": [
        0.18951858580112457,
        0.17459341883659363,
        0.1624227911233902
      ],
      "type": "Gaussian"
    },
    {
      "fit": [
        -0.3807622790336609,
        0.4452173113822937,
        1.2910844087600708
      ],
      "groups": [
        "allb1",
        "mcstat"
      ],
      "impact_r": 0.013575270771980286,
      "name": "monotop_stat_error_wzModelCR_bin1",
      "prefit": [
        -1.0,
        0.0,
        1.0
      ],
      "r": [
        0.16166922450065613,
        0.17459341883659363,
        0.1881686896085739
      ],
      "type": "Gaussian"
    },
    {
      "fit": [
        -1.4503637552261353,
        -0.6652147769927979,
        0.15576253831386566
      ],
      "groups": [
        "allb1",
        "mcstat"
      ],
      "impact_r": 0.012760505080223083,
      "name": "monotop_stat_error_wzModelCR_bin2",
      "prefit": [
        -1.0,
        0.0,
        1.0
      ],
      "r": [
        0.16306112706661224,
        0.17459341883659363,
        0.1873539239168167
      ],
      "type": "Gaussian"
    },
    {
      "fit": [
        -0.5160284638404846,
        0.2552989423274994,
        1.0563905239105225
      ],
      "groups": [
        "allb1",
        "mcstat"
      ],
      "impact_r": 0.009108483791351318,
      "name": "monotop_stat_error_wzModelCR_bin3",
      "prefit": [
        -1.0,
        0.0,
        1.0
      ],
      "r": [
        0.16634830832481384,
        0.17459341883659363,
        0.18370190262794495
      ],
      "type": "Gaussian"
    },
    {
      "fit": [
        -1.0188828706741333,
        -0.2579827904701233,
        0.5267391204833984
      ],
      "groups": [
        "allb1",
        "mcstat"
      ],
      "impact_r": 0.005275905132293701,
      "name": "monotop_stat_error_wzModelCR_bin4",
      "prefit": [
        -1.0,
        0.0,
        1.0
      ],
      "r": [
        0.17059338092803955,
        0.17459341883659363,
        0.17986932396888733
      ],
      "type": "Gaussian"
    },
    {
      "fit": [
        -0.8187565207481384,
        -0.07129698246717453,
        0.7128569483757019
      ],
      "groups": [
        "allb1",
        "mcstat"
      ],
      "impact_r": 0.0052519291639328,
      "name": "monotop_stat_error_wzModelCR_bin5",
      "prefit": [
        -1.0,
        0.0,
        1.0
      ],
      "r": [
        0.17984534800052643,
        0.17459341883659363,
        0.17145714163780212
      ],
      "type": "Gaussian"
    },
    {
      "fit": [
        -0.2492426633834839,
        0.49276620149612427,
        1.27092444896698
      ],
      "groups": [
        "allb1",
        "mcstat"
      ],
      "impact_r": 0.030701130628585815,
      "name": "monotop_stat_error_wzModelCR_bin6",
      "prefit": [
        -1.0,
        0.0,
        1.0
      ],
      "r": [
        0.20529454946517944,
        0.17459341883659363,
        0.15038847923278809
      ],
      "type": "Gaussian"
    },
    {
      "fit": [
        -0.9494643211364746,
        -0.0731501504778862,
        0.8428469896316528
      ],
      "groups": [
        "allb1",
        "mcstat"
      ],
      "impact_r": 0.07854706048965454,
      "name": "monotop_stat_error_wzModelCR_bin7",
      "prefit": [
        -1.0,
        0.0,
        1.0
      ],
      "r": [
        0.25314047932624817,
        0.17459341883659363,
        0.10874073207378387
      ],
      "type": "Gaussian"
    },
    {
      "fit": [
        0.06090069189667702,
        0.8755524158477783,
        1.7024941444396973
      ],
      "groups": [
        "allb1",
        "syst"
      ],
      "impact_r": 0.08178162574768066,
      "name": "mettrig",
      "prefit": [
        -1.0,
        0.0,
        1.0
      ],
      "r": [
        0.09299682825803757,
        0.17459341883659363,
        0.2563750445842743
      ],
      "type": "Gaussian"
    },
    {
      "fit": [
        -0.30370935797691345,
        0.1267380714416504,
        0.6127819418907166
      ],
      "groups": [
        "allb1",
        "qcd",
        "syst"
      ],
      "impact_r": 0.08557376265525818,
      "name": "renscale",
      "prefit": [
        -1.0,
        0.0,
        1.0
      ],
      "r": [
        0.254104882478714,
        0.17459341883659363,
        0.08901965618133545
      ],
      "type": "Gaussian"
    },
    {
      "fit": [
        -0.8206302523612976,
        0.04724649339914322,
        0.9274806380271912
      ],
      "groups": [
        "allb1",
        "qcd",
        "syst"
      ],
      "impact_r": 0.10208693146705627,
      "name": "facscale",
      "prefit": [
        -1.0,
        0.0,
        1.0
      ],
      "r": [
        0.2766803503036499,
        0.17459341883659363,
        0.08001671731472015
      ],
      "type": "Gaussian"
    },
    {
      "fit": [
        -0.9827732443809509,
        0.004611601587384939,
        0.9926782846450806
      ],
      "groups": [
        "allb1",
        "qcd",
        "syst"
      ],
      "impact_r": 0.01715773344039917,
      "name": "pdf",
      "prefit": [
        -1.0,
        0.0,
        1.0
      ],
      "r": [
        0.1917511522769928,
        0.17459341883659363,
        0.15969963371753693
      ],
      "type": "Gaussian"
    },
    {
      "fit": [
        -0.9748696088790894,
        -0.023381058126688004,
        0.946099579334259
      ],
      "groups": [
        "allb1",
        "other",
        "syst"
      ],
      "impact_r": 0.0023704171180725098,
      "name": "PhotonEff",
      "prefit": [
        -1.0,
        0.0,
        1.0
      ],
      "r": [
        0.1737363487482071,
        0.17459341883659363,
        0.17696383595466614
      ],
      "type": "Gaussian"
    },
    {
      "fit": [
        -0.7521898150444031,
        -0.29722946882247925,
        0.17766056954860687
      ],
      "groups": [
        "allb1",
        "qcd",
        "syst"
      ],
      "impact_r": 0.035146549344062805,
      "name": "wrenscale",
      "prefit": [
        -1.0,
        0.0,
        1.0
      ],
      "r": [
        0.20973996818065643,
        0.17459341883659363,
        0.14306141436100006
      ],
      "type": "Gaussian"
    },
    {
      "fit": [
        -0.9659942984580994,
        -0.03298168629407883,
        0.8975180387496948
      ],
      "groups": [
        "allb1",
        "qcd",
        "syst"
      ],
      "impact_r": 0.03183165192604065,
      "name": "wfacscale",
      "prefit": [
        -1.0,
        0.0,
        1.0
      ],
      "r": [
        0.20642507076263428,
        0.17459341883659363,
        0.14684849977493286
      ],
      "type": "Gaussian"
    },
    {
      "fit": [
        -0.9928492307662964,
        0.00013071743887849152,
        0.9925418496131897
      ],
      "groups": [
        "allb1",
        "qcd",
        "syst"
      ],
      "impact_r": 0.0020368993282318115,
      "name": "wpdf",
      "prefit": [
        -1.0,
        0.0,
        1.0
      ],
      "r": [
        0.17663031816482544,
        0.17459341883659363,
        0.17375175654888153
      ],
      "type": "Gaussian"
    },
    {
      "fit": [
        -0.9890275597572327,
        0.0038256628904491663,
        0.997090756893158
      ],
      "groups": [
        "allb1",
        "ewk",
        "syst"
      ],
      "impact_r": 0.007445573806762695,
      "name": "ewk",
      "prefit": [
        -1.0,
        0.0,
        1.0
      ],
      "r": [
        0.18203899264335632,
        0.17459341883659363,
        0.16844795644283295
      ],
      "type": "Gaussian"
    },
    {
      "fit": [
        -0.9808567762374878,
        -0.0016379731241613626,
        0.9733391404151917
      ],
      "groups": [
        "allb1",
        "ewk",
        "syst"
      ],
      "impact_r": 0.0234220027923584,
      "name": "ewk_missZ",
      "prefit": [
        -1.0,
        0.0,
        1.0
      ],
      "r": [
        0.19801542162895203,
        0.17459341883659363,
        0.15274286270141602
      ],
      "type": "Gaussian"
    },
    {
      "fit": [
        -0.9858490824699402,
        0.00369055918417871,
        0.99321049451828
      ],
      "groups": [
        "allb1",
        "ewk",
        "syst"
      ],
      "impact_r": 0.007615417242050171,
      "name": "ewk_missA",
      "prefit": [
        -1.0,
        0.0,
        1.0
      ],
      "r": [
        0.1822088360786438,
        0.17459341883659363,
        0.16821633279323578
      ],
      "type": "Gaussian"
    },
    {
      "fit": [
        -0.9829815030097961,
        -0.0013314582174643874,
        0.9777130484580994
      ],
      "groups": [
        "allb1",
        "ewk",
        "syst"
      ],
      "impact_r": 0.024721086025238037,
      "name": "ewk_sudZ",
      "prefit": [
        -1.0,
        0.0,
        1.0
      ],
      "r": [
        0.19931450486183167,
        0.17459341883659363,
        0.1514122635126114
      ],
      "type": "Gaussian"
    },
    {
      "fit": [
        -0.9783895015716553,
        0.007419449742883444,
        0.9939643740653992
      ],
      "groups": [
        "allb1",
        "ewk",
        "syst"
      ],
      "impact_r": 0.016351476311683655,
      "name": "ewk_sudA",
      "prefit": [
        -1.0,
        0.0,
        1.0
      ],
      "r": [
        0.19094489514827728,
        0.17459341883659363,
        0.1595725566148758
      ],
      "type": "Gaussian"
    },
    {
      "fit": [
        -0.9972894787788391,
        -0.0022920568007975817,
        0.992065966129303
      ],
      "groups": [
        "allb1",
        "ewk",
        "syst"
      ],
      "impact_r": 0.001583397388458252,
      "name": "ewkWZ",
      "prefit": [
        -1.0,
        0.0,
        1.0
      ],
      "r": [
        0.17617681622505188,
        0.17459341883659363,
        0.17418353259563446
      ],
      "type": "Gaussian"
    },
    {
      "fit": [
        -0.9949066638946533,
        -0.014020564965903759,
        0.9634198546409607
      ],
      "groups": [
        "allb1",
        "ewk",
        "syst"
      ],
      "impact_r": 0.006523609161376953,
      "name": "ewk_missW",
      "prefit": [
        -1.0,
        0.0,
        1.0
      ],
      "r": [
        0.18111702799797058,
        0.17459341883659363,
        0.169446662068367
      ],
      "type": "Gaussian"
    },
    {
      "fit": [
        -0.9954330325126648,
        -0.0022102189250290394,
        0.9905356168746948
      ],
      "groups": [
        "allb1",
        "ewk",
        "syst"
      ],
      "impact_r": 0.0035398751497268677,
      "name": "ewk_sudW",
      "prefit": [
        -1.0,
        0.0,
        1.0
      ],
      "r": [
        0.1781332939863205,
        0.17459341883659363,
        0.17229561507701874
      ],
      "type": "Gaussian"
    },
    {
      "fit": [
        -0.4316716194152832,
        0.15616944432258606,
        0.7637973427772522
      ],
      "groups": [
        "allb1",
        "mcstat"
      ],
      "impact_r": 0.06122954189777374,
      "name": "monotop_loose_stat_error_photonModelCR_bin1",
      "prefit": [
        -1.0,
        0.0,
        1.0
      ],
      "r": [
        0.11336387693881989,
        0.17459341883659363,
        0.23495566844940186
      ],
      "type": "Gaussian"
    },
    {
      "fit": [
        -0.6365463137626648,
        -0.0036137565039098263,
        0.6621221899986267
      ],
      "groups": [
        "allb1",
        "mcstat"
      ],
      "impact_r": 0.05859275162220001,
      "name": "monotop_loose_stat_error_photonModelCR_bin2",
      "prefit": [
        -1.0,
        0.0,
        1.0
      ],
      "r": [
        0.11718160659074783,
        0.17459341883659363,
        0.23318617045879364
      ],
      "type": "Gaussian"
    },
    {
      "fit": [
        -1.549469232559204,
        -0.9254629611968994,
        -0.2742328643798828
      ],
      "groups": [
        "allb1",
        "mcstat"
      ],
      "impact_r": 0.05874139070510864,
      "name": "monotop_loose_stat_error_photonModelCR_bin3",
      "prefit": [
        -1.0,
        0.0,
        1.0
      ],
      "r": [
        0.11826693266630173,
        0.17459341883659363,
        0.23333480954170227
      ],
      "type": "Gaussian"
    },
    {
      "fit": [
        -0.839819073677063,
        -0.17599725723266602,
        0.5192046761512756
      ],
      "groups": [
        "allb1",
        "mcstat"
      ],
      "impact_r": 0.041316062211990356,
      "name": "monotop_loose_stat_error_photonModelCR_bin4",
      "prefit": [
        -1.0,
        0.0,
        1.0
      ],
      "r": [
        0.1361967921257019,
        0.17459341883659363,
        0.21590948104858398
      ],
      "type": "Gaussian"
    },
    {
      "fit": [
        -0.3412083387374878,
        0.38161158561706543,
        1.1296782493591309
      ],
      "groups": [
        "allb1",
        "mcstat"
      ],
      "impact_r": 0.019499555230140686,
      "name": "monotop_loose_stat_error_photonModelCR_bin5",
      "prefit": [
        -1.0,
        0.0,
        1.0
      ],
      "r": [
        0.16183187067508698,
        0.17459341883659363,
        0.19409297406673431
      ],
      "type": "Gaussian"
    },
    {
      "fit": [
        -0.9436983466148376,
        -0.22275285422801971,
        0.5326191186904907
      ],
      "groups": [
        "allb1",
        "mcstat"
      ],
      "impact_r": 0.00546853244304657,
      "name": "monotop_loose_stat_error_photonModelCR_bin6",
      "prefit": [
        -1.0,
        0.0,
        1.0
      ],
      "r": [
        0.1800619512796402,
        0.17459341883659363,
        0.1739932894706726
      ],
      "type": "Gaussian"
    },
    {
      "fit": [
        -0.6158125400543213,
        0.24014192819595337,
        1.1067464351654053
      ],
      "groups": [
        "allb1",
        "mcstat"
      ],
      "impact_r": 0.05118207633495331,
      "name": "monotop_loose_stat_error_photonModelCR_bin7",
      "prefit": [
        -1.0,
        0.0,
        1.0
      ],
      "r": [
        0.22577549517154694,
        0.17459341883659363,
        0.1267552375793457
      ],
      "type": "Gaussian"
    },
    {
      "fit": [
        -0.6133604645729065,
        0.2766672670841217,
        1.1754610538482666
      ],
      "groups": [
        "allb1",
        "mcstat"
      ],
      "impact_r": 0.006632551550865173,
      "name": "monotop_loose_stat_error_dimuonModelCR_bin1",
      "prefit": [
        -1.0,
        0.0,
        1.0
      ],
      "r": [
        0.1812259703874588,
        0.17459341883659363,
        0.16973157227039337
      ],
      "type": "Gaussian"
    },
    {
      "fit": [
        -1.2092583179473877,
        -0.3172791004180908,
        0.5862463712692261
      ],
      "groups": [
        "allb1",
        "mcstat"
      ],
      "impact_r": 0.008772209286689758,
      "name": "monotop_loose_stat_error_dimuonModelCR_bin2",
      "prefit": [
        -1.0,
        0.0,
        1.0
      ],
      "r": [
        0.1833656281232834,
        0.17459341883659363,
        0.16758958995342255
      ],
      "type": "Gaussian"
    },
    {
      "fit": [
        -0.9934549927711487,
        -0.08849972486495972,
        0.8263281583786011
      ],
      "groups": [
        "allb1",
        "mcstat"
      ],
      "impact_r": 0.00887957215309143,
      "name": "monotop_loose_stat_error_dimuonModelCR_bin3",
      "prefit": [
        -1.0,
        0.0,
        1.0
      ],
      "r": [
        0.18347299098968506,
        0.17459341883659363,
        0.16758427023887634
      ],
      "type": "Gaussian"
    },
    {
      "fit": [
        -0.6669111251831055,
        0.2589496672153473,
        1.1918035745620728
      ],
      "groups": [
        "allb1",
        "mcstat"
      ],
      "impact_r": 0.009639933705329895,
      "name": "monotop_loose_stat_error_dimuonModelCR_bin4",
      "prefit": [
        -1.0,
        0.0,
        1.0
      ],
      "r": [
        0.18423335254192352,
        0.17459341883659363,
        0.16712220013141632
      ],
      "type": "Gaussian"
    },
    {
      "fit": [
        -0.9175844192504883,
        0.040378399193286896,
        1.0018810033798218
      ],
      "groups": [
        "allb1",
        "mcstat"
      ],
      "impact_r": 0.008530452847480774,
      "name": "monotop_loose_stat_error_dimuonModelCR_bin5",
      "prefit": [
        -1.0,
        0.0,
        1.0
      ],
      "r": [
        0.1831238716840744,
        0.17459341883659363,
        0.16808462142944336
      ],
      "type": "Gaussian"
    },
    {
      "fit": [
        -1.1846297979354858,
        -0.20497435331344604,
        0.7760169506072998
      ],
      "groups": [
        "allb1",
        "mcstat"
      ],
      "impact_r": 0.009473800659179688,
      "name": "monotop_loose_stat_error_dimuonModelCR_bin6",
      "prefit": [
        -1.0,
        0.0,
        1.0
      ],
      "r": [
        0.18406721949577332,
        0.17459341883659363,
        0.16691343486309052
      ],
      "type": "Gaussian"
    },
    {
      "fit": [
        -0.9788991212844849,
        0.009623325429856777,
        0.9985202550888062
      ],
      "groups": [
        "allb1",
        "mcstat"
      ],
      "impact_r": 0.005740165710449219,
      "name": "monotop_loose_stat_error_dimuonModelCR_bin7",
      "prefit": [
        -1.0,
        0.0,
        1.0
      ],
      "r": [
        0.18033358454704285,
        0.17459341883659363,
        0.17054231464862823
      ],
      "type": "Gaussian"
    },
    {
      "fit": [
        -0.9734262228012085,
        -0.07127934694290161,
        0.8417587876319885
      ],
      "groups": [
        "allb1",
        "mcstat"
      ],
      "impact_r": 0.0060363709926605225,
      "name": "monotop_loose_stat_error_dielectronModelCR_bin1",
      "prefit": [
        -1.0,
        0.0,
        1.0
      ],
      "r": [
        0.18062978982925415,
        0.17459341883659363,
        0.17019681632518768
      ],
      "type": "Gaussian"
    },
    {
      "fit": [
        -0.6635574102401733,
        0.23451077938079834,
        1.1441940069198608
      ],
      "groups": [
        "allb1",
        "mcstat"
      ],
      "impact_r": 0.007292464375495911,
      "name": "monotop_loose_stat_error_dielectronModelCR_bin2",
      "prefit": [
        -1.0,
        0.0,
        1.0
      ],
      "r": [
        0.18188588321208954,
        0.17459341883659363,
        0.16910716891288757
      ],
      "type": "Gaussian"
    },
    {
      "fit": [
        -0.5875470638275146,
        0.3231043815612793,
        1.2427575588226318
      ],
      "groups": [
        "allb1",
        "mcstat"
      ],
      "impact_r": 0.00734381377696991,
      "name": "monotop_loose_stat_error_dielectronModelCR_bin3",
      "prefit": [
        -1.0,
        0.0,
        1.0
      ],
      "r": [
        0.18193723261356354,
        0.17459341883659363,
        0.16921868920326233
      ],
      "type": "Gaussian"
    },
    {
      "fit": [
        -0.8219797015190125,
        0.11409299075603485,
        1.0575158596038818
      ],
      "groups": [
        "allb1",
        "mcstat"
      ],
      "impact_r": 0.008132532238960266,
      "name": "monotop_loose_stat_error_dielectronModelCR_bin4",
      "prefit": [
        -1.0,
        0.0,
        1.0
      ],
      "r": [
        0.1827259510755539,
        0.17459341883659363,
        0.16860216856002808
      ],
      "type": "Gaussian"
    },
    {
      "fit": [
        -0.9633499383926392,
        0.0015647000400349498,
        0.9703236818313599
      ],
      "groups": [
        "allb1",
        "mcstat"
      ],
      "impact_r": 0.0064130425453186035,
      "name": "monotop_loose_stat_error_dielectronModelCR_bin5",
      "prefit": [
        -1.0,
        0.0,
        1.0
      ],
      "r": [
        0.18100646138191223,
        0.17459341883659363,
        0.17001725733280182
      ],
      "type": "Gaussian"
    },
    {
      "fit": [
        -0.6947407722473145,
        0.2771340310573578,
        1.2506378889083862
      ],
      "groups": [
        "allb1",
        "mcstat"
      ],
      "impact_r": 0.0077850669622421265,
      "name": "monotop_loose_stat_error_dielectronModelCR_bin6",
      "prefit": [
        -1.0,
        0.0,
        1.0
      ],
      "r": [
        0.18237848579883575,
        0.17459341883659363,
        0.16854466497898102
      ],
      "type": "Gaussian"
    },
    {
      "fit": [
        -0.9897773861885071,
        -0.0008781723445281386,
        0.9891370534896851
      ],
      "groups": [
        "allb1",
        "mcstat"
      ],
      "impact_r": 0.0046074241399765015,
      "name": "monotop_loose_stat_error_dielectronModelCR_bin7",
      "prefit": [
        -1.0,
        0.0,
        1.0
      ],
      "r": [
        0.17920084297657013,
        0.17459341883659363,
        0.17154806852340698
      ],
      "type": "Gaussian"
    },
    {
      "fit": [
        -0.9440591931343079,
        -0.15153147280216217,
        0.6244703531265259
      ],
      "groups": [
        "allb1",
        "mcstat"
      ],
      "impact_r": 0.019507795572280884,
      "name": "monotop_loose_stat_error_wzModelCR_bin1",
      "prefit": [
        -1.0,
        0.0,
        1.0
      ],
      "r": [
        0.1550876945257187,
        0.17459341883659363,
        0.1941012144088745
      ],
      "type": "Gaussian"
    },
    {
      "fit": [
        -1.1841766834259033,
        -0.41561010479927063,
        0.35568156838417053
      ],
      "groups": [
        "allb1",
        "mcstat"
      ],
      "impact_r": 0.01564955711364746,
      "name": "monotop_loose_stat_error_wzModelCR_bin2",
      "prefit": [
        -1.0,
        0.0,
        1.0
      ],
      "r": [
        0.15952083468437195,
        0.17459341883659363,
        0.1902429759502411
      ],
      "type": "Gaussian"
    },
    {
      "fit": [
        -0.5675036311149597,
        0.17957158386707306,
        0.9624683260917664
      ],
      "groups": [
        "allb1",
        "mcstat"
      ],
      "impact_r": 0.016595914959907532,
      "name": "monotop_loose_stat_error_wzModelCR_bin3",
      "prefit": [
        -1.0,
        0.0,
        1.0
      ],
      "r": [
        0.15905480086803436,
        0.17459341883659363,
        0.19118933379650116
      ],
      "type": "Gaussian"
    },
    {
      "fit": [
        -0.7242205142974854,
        -0.03007846511900425,
        0.7479817271232605
      ],
      "groups": [
        "allb1",
        "mcstat"
      ],
      "impact_r": 0.008083119988441467,
      "name": "monotop_loose_stat_error_wzModelCR_bin4",
      "prefit": [
        -1.0,
        0.0,
        1.0
      ],
      "r": [
        0.16819743812084198,
        0.17459341883659363,
        0.1826765388250351
      ],
      "type": "Gaussian"
    },
    {
      "fit": [
        -0.6629267930984497,
        0.012769457884132862,
        0.7273979783058167
      ],
      "groups": [
        "allb1",
        "mcstat"
      ],
      "impact_r": 0.001199468970298767,
      "name": "monotop_loose_stat_error_wzModelCR_bin5",
      "prefit": [
        -1.0,
        0.0,
        1.0
      ],
      "r": [
        0.17481271922588348,
        0.17459341883659363,
        0.1757928878068924
      ],
      "type": "Gaussian"
    },
    {
      "fit": [
        -0.26009100675582886,
        0.4791450798511505,
        1.2685518264770508
      ],
      "groups": [
        "allb1",
        "mcstat"
      ],
      "impact_r": 0.008311346173286438,
      "name": "monotop_loose_stat_error_wzModelCR_bin6",
      "prefit": [
        -1.0,
        0.0,
        1.0
      ],
      "r": [
        0.18290476500988007,
        0.17459341883659363,
        0.1687764972448349
      ],
      "type": "Gaussian"
    },
    {
      "fit": [
        -1.232891321182251,
        -0.3912046551704407,
        0.5084153413772583
      ],
      "groups": [
        "allb1",
        "mcstat"
      ],
      "impact_r": 0.025727495551109314,
      "name": "monotop_loose_stat_error_wzModelCR_bin7",
      "prefit": [
        -1.0,
        0.0,
        1.0
      ],
      "r": [
        0.20032091438770294,
        0.17459341883659363,
        0.15212473273277283
      ],
      "type": "Gaussian"
    },
    {
      "fit": [
        -0.425484836101532,
        0.3845994770526886,
        1.2324820756912231
      ],
      "groups": [
        "allb1",
        "mcstat"
      ],
      "impact_r": 0.016541555523872375,
      "name": "monotop_stat_error_singlemuonwModel_bin1",
      "prefit": [
        -1.0,
        0.0,
        1.0
      ],
      "r": [
        0.15864801406860352,
        0.17459341883659363,
        0.191134974360466
      ],
      "type": "Gaussian"
    },
    {
      "fit": [
        -1.001900553703308,
        -0.25906434655189514,
        0.5360661149024963
      ],
      "groups": [
        "allb1",
        "mcstat"
      ],
      "impact_r": 0.012501001358032227,
      "name": "monotop_stat_error_singlemuonwModel_bin2",
      "prefit": [
        -1.0,
        0.0,
        1.0
      ],
      "r": [
        0.16393645107746124,
        0.17459341883659363,
        0.18709442019462585
      ],
      "type": "Gaussian"
    },
    {
      "fit": [
        -0.6252061128616333,
        0.12446540594100952,
        0.9041009545326233
      ],
      "groups": [
        "allb1",
        "mcstat"
      ],
      "impact_r": 0.006519302725791931,
      "name": "monotop_stat_error_singlemuonwModel_bin3",
      "prefit": [
        -1.0,
        0.0,
        1.0
      ],
      "r": [
        0.1697598397731781,
        0.17459341883659363,
        0.18111272156238556
      ],
      "type": "Gaussian"
    },
    {
      "fit": [
        -0.7923257350921631,
        -0.05811890587210655,
        0.719089925289154
      ],
      "groups": [
        "allb1",
        "mcstat"
      ],
      "impact_r": 0.005967006087303162,
      "name": "monotop_stat_error_singlemuonwModel_bin4",
      "prefit": [
        -1.0,
        0.0,
        1.0
      ],
      "r": [
        0.1805604249238968,
        0.17459341883659363,
        0.17122480273246765
      ],
      "type": "Gaussian"
    },
    {
      "fit": [
        -0.7831703424453735,
        -0.03941439464688301,
        0.7289328575134277
      ],
      "groups": [
        "allb1",
        "mcstat"
      ],
      "impact_r": 0.022615700960159302,
      "name": "monotop_stat_error_singlemuonwModel_bin5",
      "prefit": [
        -1.0,
        0.0,
        1.0
      ],
      "r": [
        0.19720911979675293,
        0.17459341883659363,
        0.15690597891807556
      ],
      "type": "Gaussian"
    },
    {
      "fit": [
        0.1411745399236679,
        0.8808965682983398,
        1.667320728302002
      ],
      "groups": [
        "allb1",
        "mcstat"
      ],
      "impact_r": 0.05108258128166199,
      "name": "monotop_stat_error_singlemuonwModel_bin6",
      "prefit": [
        -1.0,
        0.0,
        1.0
      ],
      "r": [
        0.22567600011825562,
        0.17459341883659363,
        0.13447988033294678
      ],
      "type": "Gaussian"
    },
    {
      "fit": [
        -0.8714017868041992,
        0.016900397837162018,
        0.9349985122680664
      ],
      "groups": [
        "allb1",
        "mcstat"
      ],
      "impact_r": 0.08798256516456604,
      "name": "monotop_stat_error_singlemuonwModel_bin7",
      "prefit": [
        -1.0,
        0.0,
        1.0
      ],
      "r": [
        0.26257598400115967,
        0.17459341883659363,
        0.10332487523555756
      ],
      "type": "Gaussian"
    },
    {
      "fit": [
        -0.1783236712217331,
        0.6474758386611938,
        1.484731912612915
      ],
      "groups": [
        "allb1",
        "mcstat"
      ],
      "impact_r": 0.011331871151924133,
      "name": "monotop_stat_error_singleelectronwModel_bin1",
      "prefit": [
        -1.0,
        0.0,
        1.0
      ],
      "r": [
        0.16379708051681519,
        0.17459341883659363,
        0.18592528998851776
      ],
      "type": "Gaussian"
    },
    {
      "fit": [
        -1.2277874946594238,
        -0.42041459679603577,
        0.40302810072898865
      ],
      "groups": [
        "allb1",
        "mcstat"
      ],
      "impact_r": 0.010340437293052673,
      "name": "monotop_stat_error_singleelectronwModel_bin2",
      "prefit": [
        -1.0,
        0.0,
        1.0
      ],
      "r": [
        0.16529203951358795,
        0.17459341883659363,
        0.1849338561296463
      ],
      "type": "Gaussian"
    },
    {
      "fit": [
        -0.49574747681617737,
        0.2714083790779114,
        1.07731032371521
      ],
      "groups": [
        "allb1",
        "mcstat"
      ],
      "impact_r": 0.005119994282722473,
      "name": "monotop_stat_error_singleelectronwModel_bin3",
      "prefit": [
        -1.0,
        0.0,
        1.0
      ],
      "r": [
        0.17109794914722443,
        0.17459341883659363,
        0.1797134131193161
      ],
      "type": "Gaussian"
    },
    {
      "fit": [
        -1.1153602600097656,
        -0.3614889681339264,
        0.4362734854221344
      ],
      "groups": [
        "allb1",
        "mcstat"
      ],
      "impact_r": 0.003967121243476868,
      "name": "monotop_stat_error_singleelectronwModel_bin4",
      "prefit": [
        -1.0,
        0.0,
        1.0
      ],
      "r": [
        0.1785605400800705,
        0.17459341883659363,
        0.17315560579299927
      ],
      "type": "Gaussian"
    },
    {
      "fit": [
        -0.827505350112915,
        -0.053175412118434906,
        0.7517105937004089
      ],
      "groups": [
        "allb1",
        "mcstat"
      ],
      "impact_r": 0.015616357326507568,
      "name": "monotop_stat_error_singleelectronwModel_bin5",
      "prefit": [
        -1.0,
        0.0,
        1.0
      ],
      "r": [
        0.1902097761631012,
        0.17459341883659363,
        0.16348782181739807
      ],
      "type": "Gaussian"
    },
    {
      "fit": [
        -1.2270530462265015,
        -0.47132083773612976,
        0.3440329134464264
      ],
      "groups": [
        "allb1",
        "mcstat"
      ],
      "impact_r": 0.04613755643367767,
      "name": "monotop_stat_error_singleelectronwModel_bin6",
      "prefit": [
        -1.0,
        0.0,
        1.0
      ],
      "r": [
        0.2207309752702713,
        0.17459341883659363,
        0.13693630695343018
      ],
      "type": "Gaussian"
    },
    {
      "fit": [
        -1.0143334865570068,
        -0.10519585758447647,
        0.8290402293205261
      ],
      "groups": [
        "allb1",
        "mcstat"
      ],
      "impact_r": 0.06802868843078613,
      "name": "monotop_stat_error_singleelectronwModel_bin7",
      "prefit": [
        -1.0,
        0.0,
        1.0
      ],
      "r": [
        0.24262210726737976,
        0.17459341883659363,
        0.12077604979276657
      ],
      "type": "Gaussian"
    },
    {
      "fit": [
        -0.9750600457191467,
        -0.24682080745697021,
        0.5047879815101624
      ],
      "groups": [
        "allb1",
        "mcstat"
      ],
      "impact_r": 0.032650530338287354,
      "name": "monotop_loose_stat_error_singlemuonwModel_bin1",
      "prefit": [
        -1.0,
        0.0,
        1.0
      ],
      "r": [
        0.14328457415103912,
        0.17459341883659363,
        0.20724394917488098
      ],
      "type": "Gaussian"
    },
    {
      "fit": [
        -1.8231946229934692,
        -1.120487928390503,
        -0.40015143156051636
      ],
      "groups": [
        "allb1",
        "mcstat"
      ],
      "impact_r": 0.027737081050872803,
      "name": "monotop_loose_stat_error_singlemuonwModel_bin2",
      "prefit": [
        -1.0,
        0.0,
        1.0
      ],
      "r": [
        0.14811208844184875,
        0.17459341883659363,
        0.20233049988746643
      ],
      "type": "Gaussian"
    },
    {
      "fit": [
        -0.6886650919914246,
        0.03281481936573982,
        0.7771121263504028
      ],
      "groups": [
        "allb1",
        "mcstat"
      ],
      "impact_r": 0.02315060794353485,
      "name": "monotop_loose_stat_error_singlemuonwModel_bin3",
      "prefit": [
        -1.0,
        0.0,
        1.0
      ],
      "r": [
        0.15232501924037933,
        0.17459341883659363,
        0.19774402678012848
      ],
      "type": "Gaussian"
    },
    {
      "fit": [
        -1.1018069982528687,
        -0.3955201506614685,
        0.32294487953186035
      ],
      "groups": [
        "allb1",
        "mcstat"
      ],
      "impact_r": 0.0101136714220047,
      "name": "monotop_loose_stat_error_singlemuonwModel_bin4",
      "prefit": [
        -1.0,
        0.0,
        1.0
      ],
      "r": [
        0.1657685488462448,
        0.17459341883659363,
        0.18470709025859833
      ],
      "type": "Gaussian"
    },
    {
      "fit": [
        -0.5839993953704834,
        0.09567976742982864,
        0.8386535048484802
      ],
      "groups": [
        "allb1",
        "mcstat"
      ],
      "impact_r": 0.0012950003147125244,
      "name": "monotop_loose_stat_error_singlemuonwModel_bin5",
      "prefit": [
        -1.0,
        0.0,
        1.0
      ],
      "r": [
        0.17588841915130615,
        0.17459341883659363,
        0.17533613741397858
      ],
      "type": "Gaussian"
    },
    {
      "fit": [
        -0.16083817183971405,
        0.5770375728607178,
        1.3322296142578125
      ],
      "groups": [
        "allb1",
        "mcstat"
      ],
      "impact_r": 0.017053410410881042,
      "name": "monotop_loose_stat_error_singlemuonwModel_bin6",
      "prefit": [
        -1.0,
        0.0,
        1.0
      ],
      "r": [
        0.19164682924747467,
        0.17459341883659363,
        0.16178125143051147
      ],
      "type": "Gaussian"
    },
    {
      "fit": [
        -1.457839012145996,
        -0.5877559185028076,
        0.3210524916648865
      ],
      "groups": [
        "allb1",
        "mcstat"
      ],
      "impact_r": 0.033973902463912964,
      "name": "monotop_loose_stat_error_singlemuonwModel_bin7",
      "prefit": [
        -1.0,
        0.0,
        1.0
      ],
      "r": [
        0.2085673213005066,
        0.17459341883659363,
        0.14624109864234924
      ],
      "type": "Gaussian"
    },
    {
      "fit": [
        -0.5051846504211426,
        0.2483040988445282,
        1.0226491689682007
      ],
      "groups": [
        "allb1",
        "mcstat"
      ],
      "impact_r": 0.02195732295513153,
      "name": "monotop_loose_stat_error_singleelectronwModel_bin1",
      "prefit": [
        -1.0,
        0.0,
        1.0
      ],
      "r": [
        0.15301036834716797,
        0.17459341883659363,
        0.19655074179172516
      ],
      "type": "Gaussian"
    },
    {
      "fit": [
        -0.39697563648223877,
        0.3294605612754822,
        1.092795968055725
      ],
      "groups": [
        "allb1",
        "mcstat"
      ],
      "impact_r": 0.02117300033569336,
      "name": "monotop_loose_stat_error_singleelectronwModel_bin2",
      "prefit": [
        -1.0,
        0.0,
        1.0
      ],
      "r": [
        0.15443266928195953,
        0.17459341883659363,
        0.195766419172287
      ],
      "type": "Gaussian"
    },
    {
      "fit": [
        -0.803256094455719,
        -0.05594232678413391,
        0.7105559706687927
      ],
      "groups": [
        "allb1",
        "mcstat"
      ],
      "impact_r": 0.018775179982185364,
      "name": "monotop_loose_stat_error_singleelectronwModel_bin3",
      "prefit": [
        -1.0,
        0.0,
        1.0
      ],
      "r": [
        0.1563127338886261,
        0.17459341883659363,
        0.193368598818779
      ],
      "type": "Gaussian"
    },
    {
      "fit": [
        -0.22704097628593445,
        0.5118939280509949,
        1.270162582397461
      ],
      "groups": [
        "allb1",
        "mcstat"
      ],
      "impact_r": 0.008301019668579102,
      "name": "monotop_loose_stat_error_singleelectronwModel_bin4",
      "prefit": [
        -1.0,
        0.0,
        1.0
      ],
      "r": [
        0.16727314889431,
        0.17459341883659363,
        0.18289443850517273
      ],
      "type": "Gaussian"
    },
    {
      "fit": [
        -0.5730467438697815,
        0.14367793500423431,
        0.8884512782096863
      ],
      "groups": [
        "allb1",
        "mcstat"
      ],
      "impact_r": 0.0017618834972381592,
      "name": "monotop_loose_stat_error_singleelectronwModel_bin5",
      "prefit": [
        -1.0,
        0.0,
        1.0
      ],
      "r": [
        0.175895094871521,
        0.17459341883659363,
        0.17283153533935547
      ],
      "type": "Gaussian"
    },
    {
      "fit": [
        -0.7117189168930054,
        0.025303591042757034,
        0.7946056127548218
      ],
      "groups": [
        "allb1",
        "mcstat"
      ],
      "impact_r": 0.01346607506275177,
      "name": "monotop_loose_stat_error_singleelectronwModel_bin6",
      "prefit": [
        -1.0,
        0.0,
        1.0
      ],
      "r": [
        0.1880594938993454,
        0.17459341883659363,
        0.164604052901268
      ],
      "type": "Gaussian"
    },
    {
      "fit": [
        -0.7225608229637146,
        0.17014414072036743,
        1.0801457166671753
      ],
      "groups": [
        "allb1",
        "mcstat"
      ],
      "impact_r": 0.021013155579566956,
      "name": "monotop_loose_stat_error_singleelectronwModel_bin7",
      "prefit": [
        -1.0,
        0.0,
        1.0
      ],
      "r": [
        0.19560657441616058,
        0.17459341883659363,
        0.15864314138889313
      ],
      "type": "Gaussian"
    },
    {
      "fit": [
        -0.4083516001701355,
        0.3998423218727112,
        1.2477697134017944
      ],
      "groups": [
        "allb1",
        "mcstat"
      ],
      "impact_r": 0.008385330438613892,
      "name": "monotop_stat_error_singlemuontopModelCR_bin0",
      "prefit": [
        -1.0,
        0.0,
        1.0
      ],
      "r": [
        0.1687314361333847,
        0.17459341883659363,
        0.18297874927520752
      ],
      "type": "Gaussian"
    },
    {
      "fit": [
        -0.5099197030067444,
        0.302901029586792,
        1.1534093618392944
      ],
      "groups": [
        "allb1",
        "mcstat"
      ],
      "impact_r": 0.0037672817707061768,
      "name": "monotop_stat_error_singlemuontopModelCR_bin1",
      "prefit": [
        -1.0,
        0.0,
        1.0
      ],
      "r": [
        0.1717207431793213,
        0.17459341883659363,
        0.1783607006072998
      ],
      "type": "Gaussian"
    },
    {
      "fit": [
        -0.005469286348670721,
        0.8032531142234802,
        1.5987507104873657
      ],
      "groups": [
        "allb1",
        "mcstat"
      ],
      "impact_r": 0.0011883527040481567,
      "name": "monotop_stat_error_singlemuontopModelCR_bin2",
      "prefit": [
        -1.0,
        0.0,
        1.0
      ],
      "r": [
        0.17578177154064178,
        0.17459341883659363,
        0.1743074506521225
      ],
      "type": "Gaussian"
    },
    {
      "fit": [
        -1.112182855606079,
        -0.29815584421157837,
        0.5454696416854858
      ],
      "groups": [
        "allb1",
        "mcstat"
      ],
      "impact_r": 0.007842853665351868,
      "name": "monotop_stat_error_singlemuontopModelCR_bin3",
      "prefit": [
        -1.0,
        0.0,
        1.0
      ],
      "r": [
        0.1824362725019455,
        0.17459341883659363,
        0.1676616221666336
      ],
      "type": "Gaussian"
    },
    {
      "fit": [
        -1.2964205741882324,
        -0.49420103430747986,
        0.33971208333969116
      ],
      "groups": [
        "allb1",
        "mcstat"
      ],
      "impact_r": 0.016749098896980286,
      "name": "monotop_stat_error_singlemuontopModelCR_bin4",
      "prefit": [
        -1.0,
        0.0,
        1.0
      ],
      "r": [
        0.1913425177335739,
        0.17459341883659363,
        0.1589810848236084
      ],
      "type": "Gaussian"
    },
    {
      "fit": [
        -0.5301560163497925,
        0.25944870710372925,
        1.095535397529602
      ],
      "groups": [
        "allb1",
        "mcstat"
      ],
      "impact_r": 0.041943877935409546,
      "name": "monotop_stat_error_singlemuontopModelCR_bin5",
      "prefit": [
        -1.0,
        0.0,
        1.0
      ],
      "r": [
        0.21653729677200317,
        0.17459341883659363,
        0.13511738181114197
      ],
      "type": "Gaussian"
    },
    {
      "fit": [
        -1.1316543817520142,
        -0.429321825504303,
        0.343670517206192
      ],
      "groups": [
        "allb1",
        "mcstat"
      ],
      "impact_r": 0.08308891206979752,
      "name": "monotop_stat_error_singlemuontopModelCR_bin6",
      "prefit": [
        -1.0,
        0.0,
        1.0
      ],
      "r": [
        0.23858341574668884,
        0.17459341883659363,
        0.09150450676679611
      ],
      "type": "Gaussian"
    },
    {
      "fit": [
        -0.7992962598800659,
        0.01217089593410492,
        0.8500161170959473
      ],
      "groups": [
        "allb1",
        "mcstat"
      ],
      "impact_r": 0.006069973111152649,
      "name": "monotop_stat_error_singleelectrontopModelCR_bin0",
      "prefit": [
        -1.0,
        0.0,
        1.0
      ],
      "r": [
        0.1695009022951126,
        0.17459341883659363,
        0.18066339194774628
      ],
      "type": "Gaussian"
    },
    {
      "fit": [
        -0.8456903100013733,
        -0.043574318289756775,
        0.7949932813644409
      ],
      "groups": [
        "allb1",
        "mcstat"
      ],
      "impact_r": 0.0031532198190689087,
      "name": "monotop_stat_error_singleelectrontopModelCR_bin1",
      "prefit": [
        -1.0,
        0.0,
        1.0
      ],
      "r": [
        0.1723596751689911,
        0.17459341883659363,
        0.17774663865566254
      ],
      "type": "Gaussian"
    },
    {
      "fit": [
        -1.6361647844314575,
        -0.8499557375907898,
        -0.0353320874273777
      ],
      "groups": [
        "allb1",
        "mcstat"
      ],
      "impact_r": 0.0009449273347854614,
      "name": "monotop_stat_error_singleelectrontopModelCR_bin2",
      "prefit": [
        -1.0,
        0.0,
        1.0
      ],
      "r": [
        0.1755383461713791,
        0.17459341883659363,
        0.17450548708438873
      ],
      "type": "Gaussian"
    },
    {
      "fit": [
        -0.5463705658912659,
        0.24978548288345337,
        1.0598740577697754
      ],
      "groups": [
        "allb1",
        "mcstat"
      ],
      "impact_r": 0.006364345550537109,
      "name": "monotop_stat_error_singleelectrontopModelCR_bin3",
      "prefit": [
        -1.0,
        0.0,
        1.0
      ],
      "r": [
        0.18095776438713074,
        0.17459341883659363,
        0.16947625577449799
      ],
      "type": "Gaussian"
    },
    {
      "fit": [
        -0.34105774760246277,
        0.46757104992866516,
        1.3023816347122192
      ],
      "groups": [
        "allb1",
        "mcstat"
      ],
      "impact_r": 0.013336509466171265,
      "name": "monotop_stat_error_singleelectrontopModelCR_bin4",
      "prefit": [
        -1.0,
        0.0,
        1.0
      ],
      "r": [
        0.1879299283027649,
        0.17459341883659363,
        0.16335202753543854
      ],
      "type": "Gaussian"
    },
    {
      "fit": [
        -1.173741102218628,
        -0.38219523429870605,
        0.4461274743080139
      ],
      "groups": [
        "allb1",
        "mcstat"
      ],
      "impact_r": 0.03792250156402588,
      "name": "monotop_stat_error_singleelectrontopModelCR_bin5",
      "prefit": [
        -1.0,
        0.0,
        1.0
      ],
      "r": [
        0.2125159204006195,
        0.17459341883659363,
        0.1393001675605774
      ],
      "type": "Gaussian"
    },
    {
      "fit": [
        -0.37219759821891785,
        0.3529648184776306,
        1.1523617506027222
      ],
      "groups": [
        "allb1",
        "mcstat"
      ],
      "impact_r": 0.05879034101963043,
      "name": "monotop_stat_error_singleelectrontopModelCR_bin6",
      "prefit": [
        -1.0,
        0.0,
        1.0
      ],
      "r": [
        0.23338375985622406,
        0.17459341883659363,
        0.13182145357131958
      ],
      "type": "Gaussian"
    },
    {
      "fit": [
        -0.7345930337905884,
        0.19548460841178894,
        1.1340606212615967
      ],
      "groups": [
        "allb1",
        "mcstat"
      ],
      "impact_r": 0.008404329419136047,
      "name": "monotop_stat_error_singlemuonwtopModelCR_bin0",
      "prefit": [
        -1.0,
        0.0,
        1.0
      ],
      "r": [
        0.1663103550672531,
        0.17459341883659363,
        0.18299774825572968
      ],
      "type": "Gaussian"
    },
    {
      "fit": [
        -1.0579742193222046,
        -0.10587713122367859,
        0.8526032567024231
      ],
      "groups": [
        "allb1",
        "mcstat"
      ],
      "impact_r": 0.003827884793281555,
      "name": "monotop_stat_error_singlemuonwtopModelCR_bin1",
      "prefit": [
        -1.0,
        0.0,
        1.0
      ],
      "r": [
        0.1710534691810608,
        0.17459341883659363,
        0.17842130362987518
      ],
      "type": "Gaussian"
    },
    {
      "fit": [
        -0.8806601166725159,
        0.05210859328508377,
        1.00338876247406
      ],
      "groups": [
        "allb1",
        "mcstat"
      ],
      "impact_r": 0.0025099515914916992,
      "name": "monotop_stat_error_singlemuonwtopModelCR_bin2",
      "prefit": [
        -1.0,
        0.0,
        1.0
      ],
      "r": [
        0.1725573092699051,
        0.17459341883659363,
        0.17710337042808533
      ],
      "type": "Gaussian"
    },
    {
      "fit": [
        -0.9742429852485657,
        -0.019531644880771637,
        0.9415650963783264
      ],
      "groups": [
        "allb1",
        "mcstat"
      ],
      "impact_r": 0.001969754695892334,
      "name": "monotop_stat_error_singlemuonwtopModelCR_bin3",
      "prefit": [
        -1.0,
        0.0,
        1.0
      ],
      "r": [
        0.17656317353248596,
        0.17459341883659363,
        0.1737876534461975
      ],
      "type": "Gaussian"
    },
    {
      "fit": [
        -0.9720055460929871,
        -0.012165184132754803,
        0.9575302600860596
      ],
      "groups": [
        "allb1",
        "mcstat"
      ],
      "impact_r": 0.006443694233894348,
      "name": "monotop_stat_error_singlemuonwtopModelCR_bin4",
      "prefit": [
        -1.0,
        0.0,
        1.0
      ],
      "r": [
        0.18103711307048798,
        0.17459341883659363,
        0.17070060968399048
      ],
      "type": "Gaussian"
    },
    {
      "fit": [
        -0.5672280192375183,
        0.3369799852371216,
        1.2557165622711182
      ],
      "groups": [
        "allb1",
        "mcstat"
      ],
      "impact_r": 0.01830621063709259,
      "name": "monotop_stat_error_singlemuonwtopModelCR_bin5",
      "prefit": [
        -1.0,
        0.0,
        1.0
      ],
      "r": [
        0.19289962947368622,
        0.17459341883659363,
        0.16177131235599518
      ],
      "type": "Gaussian"
    },
    {
      "fit": [
        -0.8345733284950256,
        0.015887422487139702,
        0.9699875712394714
      ],
      "groups": [
        "allb1",
        "mcstat"
      ],
      "impact_r": 0.094134122133255,
      "name": "monotop_stat_error_singlemuonwtopModelCR_bin6",
      "prefit": [
        -1.0,
        0.0,
        1.0
      ],
      "r": [
        0.26872754096984863,
        0.17459341883659363,
        0.12913092970848083
      ],
      "type": "Gaussian"
    },
    {
      "fit": [
        -0.4826158583164215,
        0.4209803342819214,
        1.3309102058410645
      ],
      "groups": [
        "allb1",
        "mcstat"
      ],
      "impact_r": 0.00834454596042633,
      "name": "monotop_stat_error_singleelectronwtopModelCR_bin0",
      "prefit": [
        -1.0,
        0.0,
        1.0
      ],
      "r": [
        0.1662488728761673,
        0.17459341883659363,
        0.18286184966564178
      ],
      "type": "Gaussian"
    },
    {
      "fit": [
        -1.1594388484954834,
        -0.214412122964859,
        0.7419148683547974
      ],
      "groups": [
        "allb1",
        "mcstat"
      ],
      "impact_r": 0.0036056339740753174,
      "name": "monotop_stat_error_singleelectronwtopModelCR_bin1",
      "prefit": [
        -1.0,
        0.0,
        1.0
      ],
      "r": [
        0.17113322019577026,
        0.17459341883659363,
        0.17819905281066895
      ],
      "type": "Gaussian"
    },
    {
      "fit": [
        -0.8078534603118896,
        0.12449728697538376,
        1.0700938701629639
      ],
      "groups": [
        "allb1",
        "mcstat"
      ],
      "impact_r": 0.002535223960876465,
      "name": "monotop_stat_error_singleelectronwtopModelCR_bin2",
      "prefit": [
        -1.0,
        0.0,
        1.0
      ],
      "r": [
        0.17247140407562256,
        0.17459341883659363,
        0.1771286427974701
      ],
      "type": "Gaussian"
    },
    {
      "fit": [
        -1.0989209413528442,
        -0.13948510587215424,
        0.8269532322883606
      ],
      "groups": [
        "allb1",
        "mcstat"
      ],
      "impact_r": 0.001958414912223816,
      "name": "monotop_stat_error_singleelectronwtopModelCR_bin3",
      "prefit": [
        -1.0,
        0.0,
        1.0
      ],
      "r": [
        0.17655183374881744,
        0.17459341883659363,
        0.17373010516166687
      ],
      "type": "Gaussian"
    },
    {
      "fit": [
        -0.971540629863739,
        -0.019204115495085716,
        0.9423148036003113
      ],
      "groups": [
        "allb1",
        "mcstat"
      ],
      "impact_r": 0.0052183568477630615,
      "name": "monotop_stat_error_singleelectronwtopModelCR_bin4",
      "prefit": [
        -1.0,
        0.0,
        1.0
      ],
      "r": [
        0.1798117756843567,
        0.17459341883659363,
        0.1716899573802948
      ],
      "type": "Gaussian"
    },
    {
      "fit": [
        -1.1435991525650024,
        -0.1686471849679947,
        0.8196754455566406
      ],
      "groups": [
        "allb1",
        "mcstat"
      ],
      "impact_r": 0.015562191605567932,
      "name": "monotop_stat_error_singleelectronwtopModelCR_bin5",
      "prefit": [
        -1.0,
        0.0,
        1.0
      ],
      "r": [
        0.19015561044216156,
        0.17459341883659363,
        0.1642545610666275
      ],
      "type": "Gaussian"
    },
    {
      "fit": [
        -1.0138483047485352,
        -0.09340683370828629,
        0.9089239239692688
      ],
      "groups": [
        "allb1",
        "mcstat"
      ],
      "impact_r": 0.07355673611164093,
      "name": "monotop_stat_error_singleelectronwtopModelCR_bin6",
      "prefit": [
        -1.0,
        0.0,
        1.0
      ],
      "r": [
        0.24815015494823456,
        0.17459341883659363,
        0.13882866501808167
      ],
      "type": "Gaussian"
    },
    {
      "fit": [
        -0.8840194344520569,
        -0.043478041887283325,
        0.8177146911621094
      ],
      "groups": [
        "allb1",
        "mcstat"
      ],
      "impact_r": 0.00888293981552124,
      "name": "monotop_loose_stat_error_singlemuontopModelCR_bin0",
      "prefit": [
        -1.0,
        0.0,
        1.0
      ],
      "r": [
        0.16661404073238373,
        0.17459341883659363,
        0.18347635865211487
      ],
      "type": "Gaussian"
    },
    {
      "fit": [
        -1.2134251594543457,
        -0.37983226776123047,
        0.49923044443130493
      ],
      "groups": [
        "allb1",
        "mcstat"
      ],
      "impact_r": 0.007086321711540222,
      "name": "monotop_loose_stat_error_singlemuontopModelCR_bin1",
      "prefit": [
        -1.0,
        0.0,
        1.0
      ],
      "r": [
        0.1684964895248413,
        0.17459341883659363,
        0.18167974054813385
      ],
      "type": "Gaussian"
    },
    {
      "fit": [
        -1.3680007457733154,
        -0.5328372716903687,
        0.3201107978820801
      ],
      "groups": [
        "allb1",
        "mcstat"
      ],
      "impact_r": 0.005612581968307495,
      "name": "monotop_loose_stat_error_singlemuontopModelCR_bin2",
      "prefit": [
        -1.0,
        0.0,
        1.0
      ],
      "r": [
        0.16985830664634705,
        0.17459341883659363,
        0.18020600080490112
      ],
      "type": "Gaussian"
    },
    {
      "fit": [
        -0.6510471105575562,
        0.20862840116024017,
        1.08603036403656
      ],
      "groups": [
        "allb1",
        "mcstat"
      ],
      "impact_r": 0.003089308738708496,
      "name": "monotop_loose_stat_error_singlemuontopModelCR_bin3",
      "prefit": [
        -1.0,
        0.0,
        1.0
      ],
      "r": [
        0.1721847504377365,
        0.17459341883659363,
        0.17768272757530212
      ],
      "type": "Gaussian"
    },
    {
      "fit": [
        -0.6713948249816895,
        0.154844269156456,
        1.0242491960525513
      ],
      "groups": [
        "allb1",
        "mcstat"
      ],
      "impact_r": 0.0010183602571487427,
      "name": "monotop_loose_stat_error_singlemuontopModelCR_bin4",
      "prefit": [
        -1.0,
        0.0,
        1.0
      ],
      "r": [
        0.17561177909374237,
        0.17459341883659363,
        0.17444920539855957
      ],
      "type": "Gaussian"
    },
    {
      "fit": [
        -1.015285849571228,
        -0.1876024603843689,
        0.681817889213562
      ],
      "groups": [
        "allb1",
        "mcstat"
      ],
      "impact_r": 0.006290018558502197,
      "name": "monotop_loose_stat_error_singlemuontopModelCR_bin5",
      "prefit": [
        -1.0,
        0.0,
        1.0
      ],
      "r": [
        0.18088343739509583,
        0.17459341883659363,
        0.16909775137901306
      ],
      "type": "Gaussian"
    },
    {
      "fit": [
        -1.1025198698043823,
        -0.32865381240844727,
        0.5211446285247803
      ],
      "groups": [
        "allb1",
        "mcstat"
      ],
      "impact_r": 0.03722386062145233,
      "name": "monotop_loose_stat_error_singlemuontopModelCR_bin6",
      "prefit": [
        -1.0,
        0.0,
        1.0
      ],
      "r": [
        0.21181727945804596,
        0.17459341883659363,
        0.14365646243095398
      ],
      "type": "Gaussian"
    },
    {
      "fit": [
        -0.6713216304779053,
        0.15650267899036407,
        1.0117123126983643
      ],
      "groups": [
        "allb1",
        "mcstat"
      ],
      "impact_r": 0.006450667977333069,
      "name": "monotop_loose_stat_error_singleelectrontopModelCR_bin0",
      "prefit": [
        -1.0,
        0.0,
        1.0
      ],
      "r": [
        0.1689252406358719,
        0.17459341883659363,
        0.1810440868139267
      ],
      "type": "Gaussian"
    },
    {
      "fit": [
        -0.599918782711029,
        0.23840248584747314,
        1.1047025918960571
      ],
      "groups": [
        "allb1",
        "mcstat"
      ],
      "impact_r": 0.005431830883026123,
      "name": "monotop_loose_stat_error_singleelectrontopModelCR_bin1",
      "prefit": [
        -1.0,
        0.0,
        1.0
      ],
      "r": [
        0.16990047693252563,
        0.17459341883659363,
        0.18002524971961975
      ],
      "type": "Gaussian"
    },
    {
      "fit": [
        -0.4508155882358551,
        0.3523390293121338,
        1.1721038818359375
      ],
      "groups": [
        "allb1",
        "mcstat"
      ],
      "impact_r": 0.0038641244173049927,
      "name": "monotop_loose_stat_error_singleelectrontopModelCR_bin2",
      "prefit": [
        -1.0,
        0.0,
        1.0
      ],
      "r": [
        0.17144031822681427,
        0.17459341883659363,
        0.17845754325389862
      ],
      "type": "Gaussian"
    },
    {
      "fit": [
        -0.9762778878211975,
        -0.12163841724395752,
        0.7673861980438232
      ],
      "groups": [
        "allb1",
        "mcstat"
      ],
      "impact_r": 0.002430737018585205,
      "name": "monotop_loose_stat_error_singleelectrontopModelCR_bin3",
      "prefit": [
        -1.0,
        0.0,
        1.0
      ],
      "r": [
        0.17271548509597778,
        0.17459341883659363,
        0.17702415585517883
      ],
      "type": "Gaussian"
    },
    {
      "fit": [
        -0.7905676960945129,
        0.02821158617734909,
        0.8893751502037048
      ],
      "groups": [
        "allb1",
        "mcstat"
      ],
      "impact_r": 0.001719146966934204,
      "name": "monotop_loose_stat_error_singleelectrontopModelCR_bin4",
      "prefit": [
        -1.0,
        0.0,
        1.0
      ],
      "r": [
        0.1735425740480423,
        0.17459341883659363,
        0.17631256580352783
      ],
      "type": "Gaussian"
    },
    {
      "fit": [
        -0.6282928586006165,
        0.18074603378772736,
        1.0320852994918823
      ],
      "groups": [
        "allb1",
        "mcstat"
      ],
      "impact_r": 0.004226058721542358,
      "name": "monotop_loose_stat_error_singleelectrontopModelCR_bin5",
      "prefit": [
        -1.0,
        0.0,
        1.0
      ],
      "r": [
        0.178819477558136,
        0.17459341883659363,
        0.17178252339363098
      ],
      "type": "Gaussian"
    },
    {
      "fit": [
        -0.499941349029541,
        0.29434821009635925,
        1.1175615787506104
      ],
      "groups": [
        "allb1",
        "mcstat"
      ],
      "impact_r": 0.03637911379337311,
      "name": "monotop_loose_stat_error_singleelectrontopModelCR_bin6",
      "prefit": [
        -1.0,
        0.0,
        1.0
      ],
      "r": [
        0.21097253262996674,
        0.17459341883659363,
        0.1563640832901001
      ],
      "type": "Gaussian"
    },
    {
      "fit": [
        -1.019743800163269,
        -0.04957018420100212,
        0.9272333979606628
      ],
      "groups": [
        "allb1",
        "mcstat"
      ],
      "impact_r": 0.005166858434677124,
      "name": "monotop_loose_stat_error_singlemuonwtopModelCR_bin0",
      "prefit": [
        -1.0,
        0.0,
        1.0
      ],
      "r": [
        0.1697598546743393,
        0.17459341883659363,
        0.17976027727127075
      ],
      "type": "Gaussian"
    },
    {
      "fit": [
        -1.1673476696014404,
        -0.1863475888967514,
        0.8053463697433472
      ],
      "groups": [
        "allb1",
        "mcstat"
      ],
      "impact_r": 0.002902418375015259,
      "name": "monotop_loose_stat_error_singlemuonwtopModelCR_bin1",
      "prefit": [
        -1.0,
        0.0,
        1.0
      ],
      "r": [
        0.17230969667434692,
        0.17459341883659363,
        0.1774958372116089
      ],
      "type": "Gaussian"
    },
    {
      "fit": [
        -0.9619238972663879,
        0.008223005570471287,
        0.972597062587738
      ],
      "groups": [
        "allb1",
        "mcstat"
      ],
      "impact_r": 0.0042978376150131226,
      "name": "monotop_loose_stat_error_singlemuonwtopModelCR_bin2",
      "prefit": [
        -1.0,
        0.0,
        1.0
      ],
      "r": [
        0.17039920389652252,
        0.17459341883659363,
        0.17889125645160675
      ],
      "type": "Gaussian"
    },
    {
      "fit": [
        -1.0315865278244019,
        -0.04812575876712799,
        0.9417997598648071
      ],
      "groups": [
        "allb1",
        "mcstat"
      ],
      "impact_r": 0.0010993927717208862,
      "name": "monotop_loose_stat_error_singlemuonwtopModelCR_bin3",
      "prefit": [
        -1.0,
        0.0,
        1.0
      ],
      "r": [
        0.17445310950279236,
        0.17459341883659363,
        0.17569281160831451
      ],
      "type": "Gaussian"
    },
    {
      "fit": [
        -0.9490217566490173,
        0.017465805634856224,
        0.989877462387085
      ],
      "groups": [
        "allb1",
        "mcstat"
      ],
      "impact_r": 0.0005718767642974854,
      "name": "monotop_loose_stat_error_singlemuonwtopModelCR_bin4",
      "prefit": [
        -1.0,
        0.0,
        1.0
      ],
      "r": [
        0.1750412881374359,
        0.17459341883659363,
        0.1751652956008911
      ],
      "type": "Gaussian"
    },
    {
      "fit": [
        -0.8427881598472595,
        0.102623350918293,
        1.061968207359314
      ],
      "groups": [
        "allb1",
        "mcstat"
      ],
      "impact_r": 0.002711966633796692,
      "name": "monotop_loose_stat_error_singlemuonwtopModelCR_bin5",
      "prefit": [
        -1.0,
        0.0,
        1.0
      ],
      "r": [
        0.17730538547039032,
        0.17459341883659363,
        0.17383933067321777
      ],
      "type": "Gaussian"
    },
    {
      "fit": [
        -1.3775386810302734,
        -0.31918802857398987,
        0.8244136571884155
      ],
      "groups": [
        "allb1",
        "mcstat"
      ],
      "impact_r": 0.020241081714630127,
      "name": "monotop_loose_stat_error_singlemuonwtopModelCR_bin6",
      "prefit": [
        -1.0,
        0.0,
        1.0
      ],
      "r": [
        0.19483450055122375,
        0.17459341883659363,
        0.17157043516635895
      ],
      "type": "Gaussian"
    },
    {
      "fit": [
        -0.879235029220581,
        0.0758802741765976,
        1.0342580080032349
      ],
      "groups": [
        "allb1",
        "mcstat"
      ],
      "impact_r": 0.005937591195106506,
      "name": "monotop_loose_stat_error_singleelectronwtopModelCR_bin0",
      "prefit": [
        -1.0,
        0.0,
        1.0
      ],
      "r": [
        0.16865582764148712,
        0.17459341883659363,
        0.18045367300510406
      ],
      "type": "Gaussian"
    },
    {
      "fit": [
        -0.8907648921012878,
        0.0709778219461441,
        1.0387792587280273
      ],
      "groups": [
        "allb1",
        "mcstat"
      ],
      "impact_r": 0.004020661115646362,
      "name": "monotop_loose_stat_error_singleelectronwtopModelCR_bin1",
      "prefit": [
        -1.0,
        0.0,
        1.0
      ],
      "r": [
        0.17082104086875916,
        0.17459341883659363,
        0.17861407995224
      ],
      "type": "Gaussian"
    },
    {
      "fit": [
        -0.9823204278945923,
        -0.014983133412897587,
        0.955626368522644
      ],
      "groups": [
        "allb1",
        "mcstat"
      ],
      "impact_r": 0.004087388515472412,
      "name": "monotop_loose_stat_error_singleelectronwtopModelCR_bin2",
      "prefit": [
        -1.0,
        0.0,
        1.0
      ],
      "r": [
        0.17053864896297455,
        0.17459341883659363,
        0.17868080735206604
      ],
      "type": "Gaussian"
    },
    {
      "fit": [
        -0.8879610896110535,
        0.08004695922136307,
        1.0534517765045166
      ],
      "groups": [
        "allb1",
        "mcstat"
      ],
      "impact_r": 0.0017352551221847534,
      "name": "monotop_loose_stat_error_singleelectronwtopModelCR_bin3",
      "prefit": [
        -1.0,
        0.0,
        1.0
      ],
      "r": [
        0.1735311895608902,
        0.17459341883659363,
        0.17632867395877838
      ],
      "type": "Gaussian"
    },
    {
      "fit": [
        -0.9533888101577759,
        0.018623284995555878,
        1.0023797750473022
      ],
      "groups": [
        "allb1",
        "mcstat"
      ],
      "impact_r": 0.0006395876407623291,
      "name": "monotop_loose_stat_error_singleelectronwtopModelCR_bin4",
      "prefit": [
        -1.0,
        0.0,
        1.0
      ],
      "r": [
        0.1750544309616089,
        0.17459341883659363,
        0.17523300647735596
      ],
      "type": "Gaussian"
    },
    {
      "fit": [
        -0.9620981216430664,
        0.006219854578375816,
        0.9852667450904846
      ],
      "groups": [
        "allb1",
        "mcstat"
      ],
      "impact_r": 0.003313317894935608,
      "name": "monotop_loose_stat_error_singleelectronwtopModelCR_bin5",
      "prefit": [
        -1.0,
        0.0,
        1.0
      ],
      "r": [
        0.17790673673152924,
        0.17459341883659363,
        0.17353174090385437
      ],
      "type": "Gaussian"
    },
    {
      "fit": [
        -0.7422360181808472,
        0.11833919584751129,
        1.040102243423462
      ],
      "groups": [
        "allb1",
        "mcstat"
      ],
      "impact_r": 0.02121710777282715,
      "name": "monotop_loose_stat_error_singleelectronwtopModelCR_bin6",
      "prefit": [
        -1.0,
        0.0,
        1.0
      ],
      "r": [
        0.19581052660942078,
        0.17459341883659363,
        0.16910970211029053
      ],
      "type": "Gaussian"
    }
  ]
}